feegaffe/__init__.py
feegaffe/feegaffe.py
feegaffe-1.1.11.dist-info/METADATA
feegaffe-1.1.11.dist-info/WHEEL
feegaffe-1.1.11.dist-info/top_level.txt
feegaffe-1.1.11.dist-info/RECORD
