Metadata-Version: 2.2
Name: feegaffe
Version: 1.1.11
Summary: Une librairie pour créer un bot discord rapidement
Author-email: Fée Gaffe <contact@feegaffe.fr>
